TEAL/__init__.py
TEAL/teal_standalone.py
TEAL/src/Amortization.py
TEAL/src/CashFlowPlot.py
TEAL/src/CashFlowUser.py
TEAL/src/CashFlow_ExtMod.py
TEAL/src/CashFlows.py
TEAL/src/__init__.py
TEAL/src/_utils.py
TEAL/src/main.py
teal_ravenframework-0.6.dist-info/METADATA
teal_ravenframework-0.6.dist-info/WHEEL
teal_ravenframework-0.6.dist-info/top_level.txt
teal_ravenframework-0.6.dist-info/RECORD
