Metadata-Version: 2.1
Name: teal-ravenframework
Version: 0.6
Summary: TEAL plugin for RAVEN framework
Home-page: https://github.com/idaholab/TEAL
Requires-Python: >=3.9
Requires-Dist: raven-framework >=3.1
Requires-Dist: numpy-financial
